LICENSE
MANIFEST.in
README.md
setup.py
LangDeckGen/AnkiCard.py
LangDeckGen/AnkiDeck.py
LangDeckGen/AnkiModel.py
LangDeckGen/AnkiTemplates.py
LangDeckGen/Config.py
LangDeckGen/LangDeck.py
LangDeckGen/WordList.py
LangDeckGen/__init__.py
LangDeckGen/pixabay.py
LangDeckGen.egg-info/PKG-INFO
LangDeckGen.egg-info/SOURCES.txt
LangDeckGen.egg-info/dependency_links.txt
LangDeckGen.egg-info/requires.txt
LangDeckGen.egg-info/top_level.txt
LangDeckGen/audiospeed/__init__.py
LangDeckGen/audiospeed/audiospeed.py
LangDeckGen/memecaption/__init__.py
LangDeckGen/memecaption/center-text.py
LangDeckGen/memecaption/final.py
LangDeckGen/memecaption/hello-world.py
LangDeckGen/memecaption/meme.py
LangDeckGen/memecaption/text-outline.py
LangDeckGen/memecaption/wrap-text.py
LangDeckGen/templates/LongSilence.mp3
LangDeckGen/templates/LongSilence2.mp3
LangDeckGen/templates/_montserratlight.ttf
LangDeckGen/templates/anki.css
LangDeckGen/templates/background.png
LangDeckGen/templates/missing.png
LangDeckGen/templates/placeholder.png
LangDeckGen/templates/spelling.html
LangDeckGen/templates/translate.html
LangDeckGen/templates/__pycache__/AnkiCard.cpython-39.pyc
LangDeckGen/templates/__pycache__/AnkiDeck.cpython-39.pyc
LangDeckGen/templates/__pycache__/AnkiModel.cpython-39.pyc
LangDeckGen/templates/__pycache__/AnkiTemplates.cpython-39.pyc
LangDeckGen/templates/__pycache__/Config.cpython-39.pyc
LangDeckGen/templates/__pycache__/GetFreqWordList.cpython-39.pyc
LangDeckGen/templates/__pycache__/LangDeck.cpython-39.pyc
LangDeckGen/templates/__pycache__/WordList.cpython-39.pyc
LangDeckGen/templates/__pycache__/__init__.cpython-39.pyc
LangDeckGen/templates/__pycache__/pixabay.cpython-39.pyc
LangDeckGen/templates/audiospeed/__init__.py
LangDeckGen/templates/audiospeed/audiospeed.py
LangDeckGen/templates/audiospeed/__pycache__/__init__.cpython-39.pyc
LangDeckGen/templates/audiospeed/__pycache__/audiospeed.cpython-39.pyc
LangDeckGen/templates/memecaption/README.md
LangDeckGen/templates/memecaption/__init__.py
LangDeckGen/templates/memecaption/center-text.py
LangDeckGen/templates/memecaption/final.py
LangDeckGen/templates/memecaption/hello-world.py
