Metadata-Version: 2.1
Name: LangDeckGen
Version: 0.0.6
Summary: A package to produce Anki decks from list of words for language learning including automatic audio and image generation.
Author: Rogerio Gouvea
Author-email: <rogeriog.em@gmail.com>
License: UNKNOWN
Keywords: python,tts,anki,flashcards,language
Platform: UNKNOWN
Classifier: Programming Language :: Python :: 3
Classifier: Operating System :: Unix
License-File: LICENSE
